drb/topics/sentinel2/__init__.py
drb/topics/sentinel2/_version.py
drb/topics/sentinel2/cortex.yml
drb/topics/sentinel2/aux/__init__.py
drb/topics/sentinel2/aux/cortex.yml
drb/topics/sentinel2/pdi/__init__.py
drb/topics/sentinel2/pdi/cortex.yml
drb/topics/sentinel2/pdi/datastrip/__init__.py
drb/topics/sentinel2/pdi/datastrip/cortex.yml
drb/topics/sentinel2/pdi/granule/__init__.py
drb/topics/sentinel2/pdi/granule/cortex.yml
drb/topics/sentinel2/user/__init__.py
drb/topics/sentinel2/user/cortex.yml
drb_topic_sentinel2-1.3.2.dist-info/LICENCE.txt
drb_topic_sentinel2-1.3.2.dist-info/METADATA
drb_topic_sentinel2-1.3.2.dist-info/WHEEL
drb_topic_sentinel2-1.3.2.dist-info/entry_points.txt
drb_topic_sentinel2-1.3.2.dist-info/top_level.txt
drb_topic_sentinel2-1.3.2.dist-info/RECORD
