Metadata-Version: 2.1
Name: drb-topic-sentinel2
Version: 1.3.2
Summary: Sentinel-2 topic for DRB Python
Author: GAEL Systems
Author-email: drb-python@gael.fr
License: LGPLv3
Project-URL: Source, https://gitlab.com/drb-python/topics/sentinel2
Classifier: Programming Language :: Python :: 3.8
Classifier: License :: OSI Approved :: GNU Lesser General Public License v3 (LGPLv3)
Requires-Python: >=3.8
License-File: LICENCE.txt
Requires-Dist: drb ~=2.2.0
Requires-Dist: drb-topic-safe ~=1.3.0
Requires-Dist: drb-driver-tar ~=1.3.0
